TextAnalyzerMU/__init__.py
TextAnalyzerMU/complete_analyzer.py
TextAnalyzerMU/comun_words.py
TextAnalyzerMU/extract_entities.py
TextAnalyzerMU/generate_word_cloud.py
TextAnalyzerMU/mark_key_terms.py
TextAnalyzerMU/sentence_counter.py
TextAnalyzerMU/sentiment_analysis.py
TextAnalyzerMU/summarize_text.py
TextAnalyzerMU/text_anonimaze.py
TextAnalyzerMU/text_similarity.py
TextAnalyzerMU/text_translation.py
TextAnalyzerMU-0.2.2.dist-info/METADATA
TextAnalyzerMU-0.2.2.dist-info/WHEEL
TextAnalyzerMU-0.2.2.dist-info/top_level.txt
TextAnalyzerMU-0.2.2.dist-info/RECORD
